MANIFEST.in
README.rst
setup.cfg
setup.py
concorde/__init__.py
concorde/command_line.py
concorde.egg-info/PKG-INFO
concorde.egg-info/SOURCES.txt
concorde.egg-info/dependency_links.txt
concorde.egg-info/entry_points.txt
concorde.egg-info/not-zip-safe
concorde.egg-info/requires.txt
concorde.egg-info/top_level.txt