Metadata-Version: 1.1
Name: concorde
Version: 0.1.1
Summary: Static site generator using Markdown and Jinja
Home-page: http://github.com/drcraig/concorde
Author: Dan Craig
Author-email: drcraig@gmail.com
License: MIT
Keywords: static generator markdown jinja
Platform: UNKNOWN
Classifier: Development Status :: 3 - Alpha
Classifier: License :: OSI Approved :: MIT License
Classifier: Programming Language :: Python :: 2.7
Classifier: Topic :: Internet :: WWW/HTTP :: Site Management
Classifier: Environment :: Console
